slack_request_validator/__init__.py
slack_request_validator/abstract_permission.py
slack_request_validator/permission.py
slack_request_validator/utils.py
slack_request_permission-1.0.6.dist-info/LICENSE
slack_request_permission-1.0.6.dist-info/METADATA
slack_request_permission-1.0.6.dist-info/WHEEL
slack_request_permission-1.0.6.dist-info/top_level.txt
slack_request_permission-1.0.6.dist-info/RECORD
