Metadata-Version: 2.1
Name: slack-request-permission
Version: 1.0.6
Summary: A python package that authenticates that the request is coming from slack
Home-page: https://github.com/dev-prakhar/slack-request-permission
Author: Prakhar Shrivastava
Author-email: prakhars1996@gmail.com
License: UNKNOWN
Platform: UNKNOWN
Classifier: Programming Language :: Python :: 3
Classifier: License :: OSI Approved :: MIT License
Classifier: Operating System :: OS Independent
Requires-Dist: django (>=2.0.0)
Requires-Dist: djangorestframework
